{"config":{"output_file":null,"full_docs":false,"pub_only":false,"reachable_only":false,"distro_crate":false,"signatures":false,"borrow_data":false},"version":"0.19.1","compilation":{"directory":"c:\\Users\\Anoushk\\Documents\\pointOne\\compiler","program":"C:\\Users\\Anoushk\\.rustup\\toolchains\\nightly-x86_64-pc-windows-msvc\\bin\\rls.exe","arguments":[],"output":"c:\\Users\\Anoushk\\Documents\\pointOne\\compiler\\target\\rls\\debug\\deps\\libcompiler-b07f5d36a0acb87b.rmeta"},"prelude":{"crate_id":{"name":"compiler","disambiguator":[8636144137193234220,0]},"crate_root":"src","external_crates":[{"file_name":"c:\\Users\\Anoushk\\Documents\\pointOne\\compiler\\src\\main.rs","num":1,"id":{"name":"std","disambiguator":[7837955066300100789,0]}},{"file_name":"c:\\Users\\Anoushk\\Documents\\pointOne\\compiler\\src\\main.rs","num":2,"id":{"name":"core","disambiguator":[267229713070244971,0]}},{"file_name":"c:\\Users\\Anoushk\\Documents\\pointOne\\compiler\\src\\main.rs","num":3,"id":{"name":"compiler_builtins","disambiguator":[2483068884080073872,0]}},{"file_name":"c:\\Users\\Anoushk\\Documents\\pointOne\\compiler\\src\\main.rs","num":4,"id":{"name":"rustc_std_workspace_core","disambiguator":[15143829146767998538,0]}},{"file_name":"c:\\Users\\Anoushk\\Documents\\pointOne\\compiler\\src\\main.rs","num":5,"id":{"name":"alloc","disambiguator":[16809393902746485044,0]}},{"file_name":"c:\\Users\\Anoushk\\Documents\\pointOne\\compiler\\src\\main.rs","num":6,"id":{"name":"libc","disambiguator":[1461281619930798548,0]}},{"file_name":"c:\\Users\\Anoushk\\Documents\\pointOne\\compiler\\src\\main.rs","num":7,"id":{"name":"unwind","disambiguator":[17289672492449343888,0]}},{"file_name":"c:\\Users\\Anoushk\\Documents\\pointOne\\compiler\\src\\main.rs","num":8,"id":{"name":"cfg_if","disambiguator":[3697032479024781733,0]}},{"file_name":"c:\\Users\\Anoushk\\Documents\\pointOne\\compiler\\src\\main.rs","num":9,"id":{"name":"hashbrown","disambiguator":[10450718039453305161,0]}},{"file_name":"c:\\Users\\Anoushk\\Documents\\pointOne\\compiler\\src\\main.rs","num":10,"id":{"name":"rustc_std_workspace_alloc","disambiguator":[15821436157590359832,0]}},{"file_name":"c:\\Users\\Anoushk\\Documents\\pointOne\\compiler\\src\\main.rs","num":11,"id":{"name":"rustc_demangle","disambiguator":[5787070029749851380,0]}},{"file_name":"c:\\Users\\Anoushk\\Documents\\pointOne\\compiler\\src\\main.rs","num":12,"id":{"name":"std_detect","disambiguator":[10355653586982150103,0]}},{"file_name":"c:\\Users\\Anoushk\\Documents\\pointOne\\compiler\\src\\main.rs","num":13,"id":{"name":"panic_unwind","disambiguator":[12970358751043143201,0]}}],"span":{"file_name":"src\\main.rs","byte_start":0,"byte_end":44,"line_start":1,"line_end":3,"column_start":1,"column_end":2}},"imports":[],"defs":[{"kind":"Mod","id":{"krate":0,"index":0},"span":{"file_name":"src\\main.rs","byte_start":0,"byte_end":44,"line_start":1,"line_end":3,"column_start":1,"column_end":2},"name":"","qualname":"::","value":"src\\main.rs","parent":null,"children":[{"krate":0,"index":1},{"krate":0,"index":2},{"krate":0,"index":3}],"decl_id":null,"docs":"","sig":null,"attributes":[]},{"kind":"Function","id":{"krate":0,"index":3},"span":{"file_name":"src\\main.rs","byte_start":3,"byte_end":7,"line_start":1,"line_end":1,"column_start":4,"column_end":8},"name":"main","qualname":"::main","value":"fn main()","parent":null,"children":[],"decl_id":null,"docs":"","sig":null,"attributes":[]}],"impls":[],"refs":[],"macro_refs":[],"relations":[]}